one.py
one-0.2.1.dist-info/METADATA
one-0.2.1.dist-info/RECORD
one-0.2.1.dist-info/WHEEL
one-0.2.1.dist-info/DESCRIPTION.rst
one-0.2.1.dist-info/metadata.json
one-0.2.1.dist-info/top_level.txt
