Metadata-Version: 1.1
Name: one
Version: 0.2.1
Summary: Not all nor any. Just the one.
Home-page: https://github.com/mgaitan/one
Author: Martín Gaitán
Author-email: gaitan@gmail.com
License: BSD
Keywords: one
Platform: UNKNOWN
Classifier: Development Status :: 4 - Beta
Classifier: Framework :: Django
Classifier: Intended Audience :: Developers
Classifier: License :: OSI Approved :: BSD License
Classifier: Natural Language :: English
Classifier: Programming Language :: Python :: 2
Classifier: Programming Language :: Python :: 2.5
Classifier: Programming Language :: Python :: 2.6
Classifier: Programming Language :: Python :: 2.7
Classifier: Programming Language :: Python :: 3
Classifier: Programming Language :: Python :: 3.3
Classifier: Programming Language :: Python :: 3.4
